style_guide/__init__.py
style_guide/cli.py
manaisys_style_guide-0.2.2.dist-info/METADATA
manaisys_style_guide-0.2.2.dist-info/WHEEL
manaisys_style_guide-0.2.2.dist-info/entry_points.txt
manaisys_style_guide-0.2.2.dist-info/RECORD
